{"trial_id": "47e0202e2c59324357bb7893d0f06ef2", "hyperparameters": {"space": [{"class_name": "Choice", "config": {"name": "activation", "default": "relu", "conditions": [], "values": ["relu", "tanh", "sigmoid"], "ordered": false}}, {"class_name": "Int", "config": {"name": "first_units", "default": null, "conditions": [], "min_value": 1, "max_value": 10, "step": 2, "sampling": null}}, {"class_name": "Int", "config": {"name": "num_layers", "default": null, "conditions": [], "min_value": 1, "max_value": 6, "step": 1, "sampling": null}}, {"class_name": "Int", "config": {"name": "units_0", "default": null, "conditions": [], "min_value": 1, "max_value": 10, "step": 2, "sampling": null}}, {"class_name": "Int", "config": {"name": "units_1", "default": null, "conditions": [], "min_value": 1, "max_value": 10, "step": 2, "sampling": null}}, {"class_name": "Int", "config": {"name": "units_2", "default": null, "conditions": [], "min_value": 1, "max_value": 10, "step": 2, "sampling": null}}, {"class_name": "Int", "config": {"name": "units_3", "default": null, "conditions": [], "min_value": 1, "max_value": 10, "step": 2, "sampling": null}}, {"class_name": "Int", "config": {"name": "units_4", "default": null, "conditions": [], "min_value": 1, "max_value": 10, "step": 2, "sampling": null}}, {"class_name": "Int", "config": {"name": "units_5", "default": null, "conditions": [], "min_value": 1, "max_value": 10, "step": 2, "sampling": null}}], "values": {"activation": "sigmoid", "first_units": 9, "num_layers": 5, "units_0": 3, "units_1": 5, "units_2": 5, "units_3": 7, "units_4": 3, "units_5": 5, "tuner/epochs": 6, "tuner/initial_epoch": 2, "tuner/bracket": 3, "tuner/round": 1, "tuner/trial_id": "d5a2202288002cb8de8d03e810e22f30"}}, "metrics": {"metrics": {"loss": {"direction": "min", "observations": [{"value": [0.6289734840393066], "step": 0}]}, "accuracy": {"direction": "max", "observations": [{"value": [0.9570393562316895], "step": 0}]}, "val_loss": {"direction": "min", "observations": [{"value": [0.530954897403717], "step": 0}]}, "val_accuracy": {"direction": "max", "observations": [{"value": [0.95652174949646], "step": 0}]}}}, "score": 0.95652174949646, "best_step": 0, "status": "COMPLETED"}